apparse/__init__.py
apparse/__main__.py
apparse/_version.py
apparse/base_parser.py
apparse/cli.py
apparse/iw_device_parser.py
apparse/iw_station_parser.py
apparse/iwinfo_device_parser.py
apparse/iwinfo_station_parser.py
ap_parse-0.1.0.dist-info/LICENSE
ap_parse-0.1.0.dist-info/METADATA
ap_parse-0.1.0.dist-info/WHEEL
ap_parse-0.1.0.dist-info/entry_points.txt
ap_parse-0.1.0.dist-info/top_level.txt
ap_parse-0.1.0.dist-info/RECORD
