Metadata-Version: 2.1
Name: ap-parse
Version: 0.1.0
Summary: Parser for iw and iwinfo on OpenWrt devices
Home-page: https://github.com/alexitx/ap-parse
Author: alexitx
Author-email: alexander@alexitx.com
License: MIT
Project-URL: Bug Tracker, https://github.com/alexitx/ap-parse/issues
Project-URL: Source, https://github.com/alexitx/ap-parse
Keywords: parser,parsing,iw,iwinfo,openwrt,wifi,device,station,cli,command-line
Platform: UNKNOWN
Classifier: Development Status :: 4 - Beta
Classifier: Intended Audience :: Developers
Classifier: Intended Audience :: System Administrators
Classifier: License :: OSI Approved :: MIT License
Classifier: Natural Language :: English
Classifier: Operating System :: OS Independent
Classifier: Programming Language :: Python :: 3
Classifier: Programming Language :: Python :: 3 :: Only
Classifier: Programming Language :: Python :: 3.6
Classifier: Programming Language :: Python :: 3.7
Classifier: Programming Language :: Python :: 3.8
Classifier: Programming Language :: Python :: 3.9
Classifier: Programming Language :: Python :: 3.10
Classifier: Programming Language :: Python :: Implementation :: CPython
Classifier: Topic :: Software Development :: Libraries :: Python Modules
Classifier: Topic :: Text Processing
Classifier: Topic :: Utilities
Requires-Python: >=3.6
License-File: LICENSE
